LICENSE
MANIFEST.in
README.rst
setup.cfg
setup.py
ebaws/__init__.py
ebaws/cli.py
ebaws/config.py
ebaws/core.py
ebaws/ebsysconfig.py
ebaws/ejbca.py
ebaws/errors.py
ebaws/letsencrypt.py
ebaws/registration.py
ebaws/softhsm.py
ebaws/util.py
ebaws.py.egg-info/PKG-INFO
ebaws.py.egg-info/SOURCES.txt
ebaws.py.egg-info/dependency_links.txt
ebaws.py.egg-info/entry_points.txt
ebaws.py.egg-info/requires.txt
ebaws.py.egg-info/top_level.txt
ebaws/consts/__init__.py
ebaws/tests/__init__.py
ebaws/tests/test.py