Metadata-Version: 1.1
Name: ebaws.py
Version: 0.1.4
Summary: Enigma Bridge Python Utilities for AWS
Home-page: https://github.com/EnigmaBridge/ebaws.py
Author: Enigma Bridge
Author-email: info@enigmabridge.com
License: MIT License
